LICENSE
MANIFEST.in
NEWS.md
README.md
setup.py
docs/index.html
docs/mynt.yml
docs/_assets/css/screen.css
docs/_assets/css/_sass/_base.sass
docs/_assets/css/_sass/config.rb
docs/_assets/css/_sass/screen.sass
docs/_assets/images/bg.png
docs/_assets/images/favicon.ico
docs/_assets/images/forkme.png
docs/_assets/js/mynt.min.js
docs/_assets/js/_src/mynt.js
docs/_posts/2012-03-20-Whats-new-in-mynt-v0.2.md
docs/_posts/2014-07-27-Whats-new-in-mynt-v0.3.md
docs/_templates/archive.html
docs/_templates/layout.html
docs/_templates/macros.html
docs/_templates/page.header.html
docs/_templates/post.html
docs/_templates/tag.html
docs/community/powering/index.html
docs/docs/command-line/index.html
docs/docs/configuration/index.html
docs/docs/quickstart/index.html
docs/docs/templates/index.html
docs/miscellany/changelog/index.html
docs/miscellany/upgrading/index.html
docs/news/feed.xml
docs/news/index.html
docs/news/archives/index.html
mynt/__init__.py
mynt/base.py
mynt/containers.py
mynt/core.py
mynt/exceptions.py
mynt/fs.py
mynt/main.py
mynt/processors.py
mynt/server.py
mynt/utils.py
mynt.egg-info/PKG-INFO
mynt.egg-info/SOURCES.txt
mynt.egg-info/dependency_links.txt
mynt.egg-info/entry_points.txt
mynt.egg-info/not-zip-safe
mynt.egg-info/requires.txt
mynt.egg-info/top_level.txt
mynt/parsers/__init__.py
mynt/parsers/docutils.py
mynt/parsers/hoep.py
mynt/renderers/__init__.py
mynt/renderers/jinja.py
mynt/themes/dark/feed.xml
mynt/themes/dark/index.html
mynt/themes/dark/mynt.yml
mynt/themes/dark/_assets/css/pygments.css
mynt/themes/dark/_assets/css/screen.css
mynt/themes/dark/_assets/css/_sass/_base.sass
mynt/themes/dark/_assets/css/_sass/config.rb
mynt/themes/dark/_assets/css/_sass/screen.sass
mynt/themes/dark/_assets/images/bg.png
mynt/themes/dark/_assets/images/favicon.ico
mynt/themes/dark/_assets/images/sbg.png
mynt/themes/dark/_assets/js/mynt.min.js
mynt/themes/dark/_assets/js/_src/mynt.js
mynt/themes/dark/_posts/2011-12-04-It-works.md
mynt/themes/dark/_templates/archive.html
mynt/themes/dark/_templates/layout.html
mynt/themes/dark/_templates/page.header.html
mynt/themes/dark/_templates/post.html
mynt/themes/dark/_templates/tag.html
mynt/themes/dark/archives/index.html
