Metadata-Version: 2.1
Name: mynt
Version: 0.4
Summary: A static site generator.
Home-page: https://mynt.uhnomoli.com/
Author: Andrew Fricke
Author-email: andrew@uhnomoli.com
License: BSD
Project-URL: Documentation, https://mynt.uhnomoli.com/docs/quickstart/
Project-URL: Source, https://github.com/Anomareh/mynt
Platform: any
Classifier: Development Status :: 4 - Beta
Classifier: Environment :: Console
Classifier: Environment :: Web Environment
Classifier: Intended Audience :: Developers
Classifier: Intended Audience :: End Users/Desktop
Classifier: License :: OSI Approved :: BSD License
Classifier: Operating System :: OS Independent
Classifier: Programming Language :: Python :: 3
Classifier: Topic :: Internet
Classifier: Topic :: Internet :: WWW/HTTP
Classifier: Topic :: Text Processing
Classifier: Topic :: Utilities
Requires-Python: ~=3.5
Provides-Extra: reST
